LICENSE
MANIFEST.in
README
setup.py
mltool/__init__.py
mltool/decisiontree.py
mltool/evaluate.py
mltool/forest.py
mltool/predict.py
mltool/utils.py
mltool.egg-info/PKG-INFO
mltool.egg-info/SOURCES.txt
mltool.egg-info/dependency_links.txt
mltool.egg-info/requires.txt
mltool.egg-info/top_level.txt
scripts/mltool