Metadata-Version: 1.0
Name: mltool
Version: 0.5.1b
Summary: Machine learning tool for regression.
Home-page: https://bitbucket.org/duilio/mltool
Author: Maurizio Sambati
Author-email: maurizio@skicelab.com
License: Copyright (C) 2012 Maurizio Sambati
